cps_deckenmalerei/__init__.py
cps_deckenmalerei/_version.py
cps_deckenmalerei/buildings.py
cps_deckenmalerei/entity.py
cps_deckenmalerei/object.py
cps_deckenmalerei/query.py
cps_deckenmalerei/record.py
cps_deckenmalerei/schema.sql
cps_deckenmalerei/scrape.py
cps_deckenmalerei/snarf.py
cps_deckenmalerei/sqlite.py
cps_deckenmalerei/wbset.py
cps_deckenmalerei-1.0.1.dist-info/entry_points.txt
cps_deckenmalerei-1.0.1.dist-info/licenses/LICENSE
cps_deckenmalerei-1.0.1.dist-info/WHEEL
cps_deckenmalerei-1.0.1.dist-info/METADATA
cps_deckenmalerei-1.0.1.dist-info/RECORD
