Metadata-Version: 2.4
Name: cps_deckenmalerei
Version: 1.0.1
Summary: CPS Ceiling Paintings
Author: Darron Broad
Requires-Python: >=3.9
Classifier: Programming Language :: Python :: 3
Classifier: Operating System :: OS Independent
License-File: LICENSE
Requires-Dist: WikibaseIntegrator>=0.12
Requires-Dist: lxml
Requires-Dist: beautifulsoup4
Requires-Dist: selenium
Requires-Dist: translate
Requires-Dist: cps-sget
Requires-Dist: cps-wb
Project-URL: Documentation, https://wiki.kewl.org/projects:deckenmalerei
